micro_orm/__init__.py
micro_orm/micro_orm.py
micro_orm/fields/__init__.py
micro_orm/fields/exceptions.py
micro_orm/models/__init__.py
micro_orm/query/__init__.py
micro_orm/query/exceptions.py
micro_orm-0.0.10.dist-info/LICENSE
micro_orm-0.0.10.dist-info/METADATA
micro_orm-0.0.10.dist-info/WHEEL
micro_orm-0.0.10.dist-info/top_level.txt
micro_orm-0.0.10.dist-info/RECORD
