Metadata-Version: 2.1
Name: micro-orm
Version: 0.0.10
Summary: A small orm for database uses, based on django ORM
Home-page: https://github.com/RooYnnER/micro-orm
Author: Royner Chavarría
Author-email: roynercharo@hotmail.com
License: MIT
Platform: UNKNOWN
Classifier: Programming Language :: Python :: 3
Classifier: License :: OSI Approved :: MIT License
Classifier: Operating System :: OS Independent
Requires-Python: >=3.5
Requires-Dist: pymysql
